bamboost/__init__.py
bamboost/__init__.pyi
bamboost/_config.py
bamboost/_typing.py
bamboost/constants.py
bamboost/exceptions.py
bamboost/plugins.py
bamboost/utilities.py
bamboost/_repr/hdf5_group.html
bamboost/_repr/icon.png
bamboost/_repr/icon.txt
bamboost/_repr/manager.html
bamboost/_repr/series.html
bamboost/_repr/simulation.html
bamboost/cli/__init__.py
bamboost/cli/__main__.py
bamboost/cli/_completion.py
bamboost/cli/_fast_index_query.py
bamboost/cli/_render.py
bamboost/cli/alias.py
bamboost/cli/app.py
bamboost/cli/common.py
bamboost/cli/config.py
bamboost/cli/indexing.py
bamboost/core/__init__.py
bamboost/core/__init__.pyi
bamboost/core/collection.py
bamboost/core/remote.py
bamboost/core/utilities.py
bamboost/core/hdf5/__init__.py
bamboost/core/hdf5/attrsdict.py
bamboost/core/hdf5/file.py
bamboost/core/hdf5/filemap.py
bamboost/core/hdf5/hdf5path.py
bamboost/core/hdf5/ref.py
bamboost/core/simulation/__init__.py
bamboost/core/simulation/base.py
bamboost/core/simulation/dict.py
bamboost/core/simulation/groups.py
bamboost/core/simulation/series.py
bamboost/core/simulation/xdmf.py
bamboost/index/__init__.py
bamboost/index/_filtering.py
bamboost/index/base.py
bamboost/index/schema.py
bamboost/index/store.py
bamboost/mpi/__init__.py
bamboost/mpi/mock.py
bamboost/mpi/utilities.py
bamboost/plugins_dev/__init__.py
bamboost/plugins_dev/fenics.py
bamboost-0.11.0.dist-info/METADATA
bamboost-0.11.0.dist-info/WHEEL
bamboost-0.11.0.dist-info/entry_points.txt
bamboost-0.11.0.dist-info/licenses/LICENSE
bamboost-0.11.0.dist-info/RECORD
