Metadata-Version: 2.4
Name: bamboost
Version: 0.11.0
Summary: A light weight scientific data management system using HDF5
Project-URL: Homepage, https://bamboost.ch/
Project-URL: repository, https://gitlab.com/cmbm-ethz/bamboost
Project-URL: changelog, https://gitlab.com/cmbm-ethz/bamboost/-/tree/main/CHANGELOG.md
Author-email: Flavio Lorez <florez@ethz.ch>
License-Expression: MIT
License-File: LICENSE
Keywords: database,database-manager,hdf5
Classifier: Development Status :: 4 - Beta
Classifier: Programming Language :: Python
Classifier: Programming Language :: Python :: 3
Requires-Python: >=3.10
Requires-Dist: h5py
Requires-Dist: jinja2>=3.1.5
Requires-Dist: lazy-loader>=0.4
Requires-Dist: numpy
Requires-Dist: pandas
Requires-Dist: pyyaml>=6.0.3
Requires-Dist: sqlalchemy>=2.0.36
Requires-Dist: typer>=0.15.2
Requires-Dist: typing-extensions>=4.12.2
